ms_deisotope/__init__.py
ms_deisotope/averagine.py
ms_deisotope/config.py
ms_deisotope/constants.py
ms_deisotope/envelope_statistics.py
ms_deisotope/peak_set.py
ms_deisotope/plot.py
ms_deisotope/processor.py
ms_deisotope/scoring.py
ms_deisotope/spectrum_graph.py
ms_deisotope/utils.py
ms_deisotope/version.py
ms_deisotope/_c/__init__.py
ms_deisotope/_c/averagine.c
ms_deisotope/_c/averagine.cp311-win_amd64.pyd
ms_deisotope/_c/averagine.pxd
ms_deisotope/_c/averagine.pyx
ms_deisotope/_c/compat.h
ms_deisotope/_c/compat.pxd
ms_deisotope/_c/deconvoluter_base.c
ms_deisotope/_c/deconvoluter_base.cp311-win_amd64.pyd
ms_deisotope/_c/deconvoluter_base.pxd
ms_deisotope/_c/deconvoluter_base.pyx
ms_deisotope/_c/peak_set.c
ms_deisotope/_c/peak_set.cp311-win_amd64.pyd
ms_deisotope/_c/peak_set.pxd
ms_deisotope/_c/peak_set.pyx
ms_deisotope/_c/scoring.c
ms_deisotope/_c/scoring.cp311-win_amd64.pyd
ms_deisotope/_c/scoring.pxd
ms_deisotope/_c/scoring.pyx
ms_deisotope/_c/similarity_methods.c
ms_deisotope/_c/similarity_methods.cp311-win_amd64.pyd
ms_deisotope/_c/similarity_methods.pyx
ms_deisotope/_c/spectrum_graph.c
ms_deisotope/_c/spectrum_graph.cp311-win_amd64.pyd
ms_deisotope/_c/spectrum_graph.pxd
ms_deisotope/_c/spectrum_graph.pyx
ms_deisotope/_c/units.c
ms_deisotope/_c/units.cp311-win_amd64.pyd
ms_deisotope/_c/units.pyx
ms_deisotope/_c/utils.c
ms_deisotope/_c/utils.cp311-win_amd64.pyd
ms_deisotope/_c/utils.pxd
ms_deisotope/_c/utils.pyx
ms_deisotope/_c/feature_map/__init__.py
ms_deisotope/_c/feature_map/dependence_network.c
ms_deisotope/_c/feature_map/dependence_network.cp311-win_amd64.pyd
ms_deisotope/_c/feature_map/dependence_network.pxd
ms_deisotope/_c/feature_map/dependence_network.pyx
ms_deisotope/_c/feature_map/feature_fit.c
ms_deisotope/_c/feature_map/feature_fit.cp311-win_amd64.pyd
ms_deisotope/_c/feature_map/feature_fit.pxd
ms_deisotope/_c/feature_map/feature_fit.pyx
ms_deisotope/_c/feature_map/feature_graph.c
ms_deisotope/_c/feature_map/feature_graph.cp311-win_amd64.pyd
ms_deisotope-0.0.60.dist-info/licenses/LICENSE
ms_deisotope-0.0.60.dist-info/METADATA
ms_deisotope-0.0.60.dist-info/WHEEL
ms_deisotope-0.0.60.dist-info/entry_points.txt
ms_deisotope-0.0.60.dist-info/top_level.txt
ms_deisotope-0.0.60.dist-info/RECORD
