Metadata-Version: 2.4
Name: ms_deisotope
Version: 0.0.60
Summary: Access, Deisotope, and Charge Deconvolute Mass Spectra
Author: Joshua Klein
Author-email: jaklein@bu.edu
Project-URL: Documentation, https://mobiusklein.github.io/ms_deisotope
Project-URL: Source Code, https://github.com/mobiusklein/ms_deisotope
Project-URL: Issue Tracker, https://github.com/mobiusklein/ms_deisotope/issues
Project-URL: Change Log, https://github.com/mobiusklein/ms_deisotope/blob/master/CHANGELOG.md
Classifier: Development Status :: 3 - Alpha
Classifier: Intended Audience :: Science/Research
Classifier: License :: OSI Approved :: Apache Software License
Classifier: Topic :: Scientific/Engineering :: Bio-Informatics
Requires-Python: >3.8
License-File: LICENSE
Requires-Dist: numpy>=2.0.0; python_version >= "3.9"
Requires-Dist: numpy; python_version < "3.9"
Requires-Dist: scipy
Requires-Dist: six
Requires-Dist: dill
Requires-Dist: ms_peak_picker>=0.1.46
Requires-Dist: brain-isotopic-distribution>=1.5.8
Requires-Dist: pyteomics>=4.6.2
Requires-Dist: lxml
Requires-Dist: psims>=1.3.0
Requires-Dist: python-idzip>=0.3.2
Requires-Dist: pyzstd
Provides-Extra: com
Requires-Dist: comtypes; extra == "com"
Provides-Extra: net
Requires-Dist: pythonnet; extra == "net"
Provides-Extra: plot
Requires-Dist: matplotlib; extra == "plot"
Provides-Extra: cli
Requires-Dist: click>=8.2; extra == "cli"
Provides-Extra: mzmlb
Requires-Dist: h5py; extra == "mzmlb"
Requires-Dist: hdf5plugin; extra == "mzmlb"
Provides-Extra: all
Requires-Dist: comtypes; extra == "all"
Requires-Dist: pythonnet; extra == "all"
Requires-Dist: matplotlib; extra == "all"
Requires-Dist: click>=8.2; extra == "all"
Requires-Dist: h5py; extra == "all"
Requires-Dist: hdf5plugin; extra == "all"
Dynamic: author
Dynamic: author-email
Dynamic: classifier
Dynamic: description
Dynamic: license-file
Dynamic: project-url
Dynamic: provides-extra
Dynamic: requires-dist
Dynamic: requires-python
Dynamic: summary
